neutronapi/__init__.py
neutronapi/application.py
neutronapi/background.py
neutronapi/base.py
neutronapi/cli.py
neutronapi/conf.py
neutronapi/encoders.py
neutronapi/exceptions.py
neutronapi/http.py
neutronapi/parsers.py
neutronapi/api/__init__.py
neutronapi/api/exceptions.py
neutronapi/authentication/__init__.py
neutronapi/authentication/base.py
neutronapi/authentication/exceptions.py
neutronapi/commands/__init__.py
neutronapi/commands/base.py
neutronapi/commands/makemigrations.py
neutronapi/commands/migrate.py
neutronapi/commands/shell.py
neutronapi/commands/start.py
neutronapi/commands/startapp.py
neutronapi/commands/startproject.py
neutronapi/commands/test.py
neutronapi/db/__init__.py
neutronapi/db/connection.py
neutronapi/db/exceptions.py
neutronapi/db/fields.py
neutronapi/db/migration_tracker.py
neutronapi/db/migrations.py
neutronapi/db/models.py
neutronapi/db/queryset.py
neutronapi/db/providers/__init__.py
neutronapi/db/providers/base.py
neutronapi/db/providers/postgres.py
neutronapi/db/providers/sqlite.py
neutronapi/middleware/__init__.py
neutronapi/middleware/allowed_hosts.py
neutronapi/middleware/compression.py
neutronapi/middleware/cors.py
neutronapi/middleware/exceptions.py
neutronapi/middleware/routing.py
neutronapi/openapi/__init__.py
neutronapi/openapi/exceptions.py
neutronapi/openapi/openapi.py
neutronapi/openapi/swagger.py
neutronapi/utils/__init__.py
neutronapi/utils/ids.py
neutronapi-0.5.12.dist-info/licenses/LICENSE
neutronapi-0.5.12.dist-info/METADATA
neutronapi-0.5.12.dist-info/WHEEL
neutronapi-0.5.12.dist-info/entry_points.txt
neutronapi-0.5.12.dist-info/top_level.txt
neutronapi-0.5.12.dist-info/RECORD
