Metadata-Version: 2.4
Name: neutronapi
Version: 0.5.12
Summary: A modern, high-performance ASGI-based Python web framework.
Author-email: Aaron Kazah <aaron@neutronapi.com>
License-Expression: MIT
Keywords: api,framework,async,fastapi,uvicorn,orm,migrations,background-tasks,dependency-injection,typing
Classifier: Development Status :: 4 - Beta
Classifier: Intended Audience :: Developers
Classifier: Operating System :: OS Independent
Classifier: Programming Language :: Python :: 3
Classifier: Programming Language :: Python :: 3.12
Classifier: Topic :: Internet :: WWW/HTTP :: HTTP Servers
Classifier: Topic :: Software Development :: Libraries :: Python Modules
Classifier: Framework :: AsyncIO
Requires-Python: >=3.12
License-File: LICENSE
Requires-Dist: uvicorn[standard]>=0.23.0
Requires-Dist: uvloop>=0.17.0
Requires-Dist: aiosqlite>=0.19.0
Requires-Dist: PyJWT>=2.8.0
Requires-Dist: bcrypt>=4.0.0
Requires-Dist: watchdog>=3.0.0
Provides-Extra: postgres
Requires-Dist: asyncpg>=0.29.0; extra == "postgres"
Provides-Extra: dev
Requires-Dist: httpx>=0.24.0; extra == "dev"
Requires-Dist: pytest>=7.0.0; extra == "dev"
Requires-Dist: pytest-asyncio>=0.21.0; extra == "dev"
Dynamic: license-file
